README.txt
code.py
setup.py
sagemaker_devcloud_rp.egg-info/PKG-INFO
sagemaker_devcloud_rp.egg-info/SOURCES.txt
sagemaker_devcloud_rp.egg-info/dependency_links.txt
sagemaker_devcloud_rp.egg-info/top_level.txt